[{"pk": 1, "model": "pokeapi.type", "fields": {"color": "", "name": "normal"}}, {"pk": 3, "model": "pokeapi.type", "fields": {"color": "", "name": "flying"}}, {"pk": 4, "model": "pokeapi.type", "fields": {"color": "", "name": "poison"}}, {"pk": 5, "model": "pokeapi.type", "fields": {"color": "", "name": "ground"}}, {"pk": 6, "model": "pokeapi.type", "fields": {"color": "", "name": "rock"}}, {"pk": 7, "model": "pokeapi.type", "fields": {"color": "", "name": "bug"}}, {"pk": 8, "model": "pokeapi.type", "fields": {"color": "", "name": "ghost"}}, {"pk": 9, "model": "pokeapi.type", "fields": {"color": "", "name": "steel"}}, {"pk": 10, "model": "pokeapi.type", "fields": {"color": "", "name": "fire"}}, {"pk": 11, "model": "pokeapi.type", "fields": {"color": "", "name": "water"}}, {"pk": 12, "model": "pokeapi.type", "fields": {"color": "", "name": "grass"}}, {"pk": 13, "model": "pokeapi.type", "fields": {"color": "", "name": "electric"}}, {"pk": 14, "model": "pokeapi.type", "fields": {"color": "", "name": "psychic"}}, {"pk": 15, "model": "pokeapi.type", "fields": {"color": "", "name": "ice"}}, {"pk": 16, "model": "pokeapi.type", "fields": {"color": "", "name": "dragon"}}, {"pk": 17, "model": "pokeapi.type", "fields": {"color": "", "name": "dark"}}, {"pk": 18, "model": "pokeapi.type", "fields": {"color": "", "name": "fairy"}}, {"pk": 19, "model": "pokeapi.type", "fields": {"color": "", "name": "fighting"}}, {"pk": 1, "model": "pokeapi.pokemon", "fields": {"name": "Fletchinder", "types": []}}, {"pk": 2, "model": "pokeapi.pokemon", "fields": {"name": "Fletchinder", "types": [3, 10]}}, {"pk": 3, "model": "pokeapi.pokemon", "fields": {"name": "Seedot", "types": [12]}}, {"pk": 4, "model": "pokeapi.pokemon", "fields": {"name": "Buneary", "types": [1]}}, {"pk": 5, "model": "pokeapi.pokemon", "fields": {"name": "Duosion", "types": [14]}}, {"pk": 6, "model": "pokeapi.pokemon", "fields": {"name": "Mandibuzz", "types": [3, 17]}}, {"pk": 7, "model": "pokeapi.pokemon", "fields": {"name": "Swellow", "types": [1, 3]}}, {"pk": 8, "model": "pokeapi.pokemon", "fields": {"name": "Eevee", "types": [1]}}, {"pk": 9, "model": "pokeapi.pokemon", "fields": {"name": "Poliwrath", "types": []}}, {"pk": 10, "model": "pokeapi.pokemon", "fields": {"name": "Fletchinder", "types": [3, 10]}}, {"pk": 11, "model": "pokeapi.pokemon", "fields": {"name": "Seedot", "types": [12]}}, {"pk": 12, "model": "pokeapi.pokemon", "fields": {"name": "Buneary", "types": [1]}}, {"pk": 13, "model": "pokeapi.pokemon", "fields": {"name": "Duosion", "types": [14]}}, {"pk": 14, "model": "pokeapi.pokemon", "fields": {"name": "Mandibuzz", "types": [3, 17]}}, {"pk": 15, "model": "pokeapi.pokemon", "fields": {"name": "Swellow", "types": [1, 3]}}, {"pk": 16, "model": "pokeapi.pokemon", "fields": {"name": "Eevee", "types": [1]}}, {"pk": 17, "model": "pokeapi.pokemon", "fields": {"name": "Poliwrath", "types": []}}, {"pk": 18, "model": "pokeapi.pokemon", "fields": {"name": "Fletchinder", "types": [3, 10]}}, {"pk": 19, "model": "pokeapi.pokemon", "fields": {"name": "Seedot", "types": [12]}}, {"pk": 20, "model": "pokeapi.pokemon", "fields": {"name": "Buneary", "types": [1]}}, {"pk": 21, "model": "pokeapi.pokemon", "fields": {"name": "Duosion", "types": [14]}}, {"pk": 22, "model": "pokeapi.pokemon", "fields": {"name": "Mandibuzz", "types": [3, 17]}}, {"pk": 23, "model": "pokeapi.pokemon", "fields": {"name": "Swellow", "types": [1, 3]}}, {"pk": 24, "model": "pokeapi.pokemon", "fields": {"name": "Eevee", "types": [1]}}, {"pk": 25, "model": "pokeapi.pokemon", "fields": {"name": "Poliwrath", "types": []}}, {"pk": 26, "model": "pokeapi.pokemon", "fields": {"name": "Fletchinder", "types": [3, 10]}}, {"pk": 27, "model": "pokeapi.pokemon", "fields": {"name": "Seedot", "types": [12]}}, {"pk": 28, "model": "pokeapi.pokemon", "fields": {"name": "Buneary", "types": [1]}}, {"pk": 29, "model": "pokeapi.pokemon", "fields": {"name": "Duosion", "types": [14]}}, {"pk": 30, "model": "pokeapi.pokemon", "fields": {"name": "Mandibuzz", "types": [3, 17]}}, {"pk": 31, "model": "pokeapi.pokemon", "fields": {"name": "Swellow", "types": [1, 3]}}, {"pk": 32, "model": "pokeapi.pokemon", "fields": {"name": "Eevee", "types": [1]}}, {"pk": 33, "model": "pokeapi.pokemon", "fields": {"name": "Poliwrath", "types": [11, 19]}}, {"pk": 34, "model": "pokeapi.pokemon", "fields": {"name": "Emolga", "types": [3, 13]}}, {"pk": 35, "model": "pokeapi.pokemon", "fields": {"name": "Butterfree", "types": [3, 7]}}, {"pk": 36, "model": "pokeapi.pokemon", "fields": {"name": "Gliscor", "types": [3, 5]}}, {"pk": 37, "model": "pokeapi.pokemon", "fields": {"name": "Wobbuffet", "types": [14]}}, {"pk": 38, "model": "pokeapi.pokemon", "fields": {"name": "Cresselia", "types": [14]}}, {"pk": 39, "model": "pokeapi.pokemon", "fields": {"name": "Tangela", "types": [12]}}, {"pk": 40, "model": "pokeapi.pokemon", "fields": {"name": "Roggenrola", "types": [6]}}, {"pk": 41, "model": "pokeapi.pokemon", "fields": {"name": "Frogadier", "types": [11]}}, {"pk": 42, "model": "pokeapi.pokemon", "fields": {"name": "Absol", "types": [17]}}, {"pk": 43, "model": "pokeapi.pokemon", "fields": {"name": "Azurill", "types": [1]}}, {"pk": 44, "model": "pokeapi.pokemon", "fields": {"name": "Magnemite", "types": [9, 13]}}, {"pk": 45, "model": "pokeapi.pokemon", "fields": {"name": "Bergmite", "types": [15]}}, {"pk": 46, "model": "pokeapi.pokemon", "fields": {"name": "Linoone", "types": [1]}}, {"pk": 47, "model": "pokeapi.pokemon", "fields": {"name": "Lillipup", "types": [1]}}, {"pk": 48, "model": "pokeapi.pokemon", "fields": {"name": "Cleffa", "types": [1]}}, {"pk": 49, "model": "pokeapi.pokemon", "fields": {"name": "Lapras", "types": [11, 15]}}, {"pk": 50, "model": "pokeapi.pokemon", "fields": {"name": "Seviper", "types": [4]}}, {"pk": 51, "model": "pokeapi.pokemon", "fields": {"name": "Krookodile", "types": [5, 17]}}, {"pk": 52, "model": "pokeapi.pokemon", "fields": {"name": "Mankey", "types": [19]}}, {"pk": 53, "model": "pokeapi.pokemon", "fields": {"name": "Mawile", "types": [9]}}, {"pk": 54, "model": "pokeapi.pokemon", "fields": {"name": "Gothorita", "types": [14]}}, {"pk": 55, "model": "pokeapi.pokemon", "fields": {"name": "Palkia", "types": [11, 16]}}, {"pk": 56, "model": "pokeapi.pokemon", "fields": {"name": "Raticate", "types": [1]}}, {"pk": 57, "model": "pokeapi.pokemon", "fields": {"name": "Snubbull", "types": [1]}}, {"pk": 58, "model": "pokeapi.pokemon", "fields": {"name": "Klink", "types": [9]}}, {"pk": 59, "model": "pokeapi.pokemon", "fields": {"name": "Houndour", "types": [10, 17]}}, {"pk": 60, "model": "pokeapi.pokemon", "fields": {"name": "Stoutland", "types": [1]}}, {"pk": 61, "model": "pokeapi.pokemon", "fields": {"name": "Aggron", "types": [6, 9]}}, {"pk": 62, "model": "pokeapi.pokemon", "fields": {"name": "Slowbro", "types": [11, 14]}}, {"pk": 63, "model": "pokeapi.pokemon", "fields": {"name": "Slakoth", "types": [1]}}, {"pk": 64, "model": "pokeapi.pokemon", "fields": {"name": "Celebi", "types": [12, 14]}}, {"pk": 65, "model": "pokeapi.pokemon", "fields": {"name": "Ampharos", "types": [13]}}, {"pk": 66, "model": "pokeapi.pokemon", "fields": {"name": "Omastar", "types": [6, 11]}}, {"pk": 67, "model": "pokeapi.pokemon", "fields": {"name": "Purugly", "types": [1]}}, {"pk": 68, "model": "pokeapi.pokemon", "fields": {"name": "Binacle", "types": [6, 11]}}, {"pk": 69, "model": "pokeapi.pokemon", "fields": {"name": "Zorua", "types": [17]}}, {"pk": 70, "model": "pokeapi.pokemon", "fields": {"name": "Ledian", "types": [3, 7]}}, {"pk": 71, "model": "pokeapi.pokemon", "fields": {"name": "Walrein", "types": [11, 15]}}, {"pk": 72, "model": "pokeapi.pokemon", "fields": {"name": "Basculin", "types": [11]}}, {"pk": 73, "model": "pokeapi.pokemon", "fields": {"name": "Heliolisk", "types": [1, 13]}}, {"pk": 74, "model": "pokeapi.pokemon", "fields": {"name": "Durant", "types": [7, 9]}}, {"pk": 75, "model": "pokeapi.pokemon", "fields": {"name": "Swirlix", "types": [18]}}, {"pk": 76, "model": "pokeapi.pokemon", "fields": {"name": "Huntail", "types": [11]}}, {"pk": 77, "model": "pokeapi.pokemon", "fields": {"name": "Regirock", "types": [6]}}, {"pk": 78, "model": "pokeapi.pokemon", "fields": {"name": "Kabutops", "types": [6, 11]}}, {"pk": 79, "model": "pokeapi.pokemon", "fields": {"name": "Rufflet", "types": [1, 3]}}, {"pk": 80, "model": "pokeapi.pokemon", "fields": {"name": "Metagross", "types": [9, 14]}}, {"pk": 81, "model": "pokeapi.pokemon", "fields": {"name": "Pansear", "types": [10]}}, {"pk": 82, "model": "pokeapi.pokemon", "fields": {"name": "Doduo", "types": [1, 3]}}, {"pk": 83, "model": "pokeapi.pokemon", "fields": {"name": "Rotom", "types": [3, 13]}}, {"pk": 84, "model": "pokeapi.pokemon", "fields": {"name": "Pansage", "types": [12]}}, {"pk": 85, "model": "pokeapi.pokemon", "fields": {"name": "Crawdaunt", "types": [11, 17]}}, {"pk": 86, "model": "pokeapi.pokemon", "fields": {"name": "Crobat", "types": [3, 4]}}, {"pk": 87, "model": "pokeapi.pokemon", "fields": {"name": "Swanna", "types": [3, 11]}}, {"pk": 88, "model": "pokeapi.pokemon", "fields": {"name": "Ducklett", "types": [3, 11]}}, {"pk": 89, "model": "pokeapi.pokemon", "fields": {"name": "Skuntank", "types": [4, 17]}}, {"pk": 90, "model": "pokeapi.pokemon", "fields": {"name": "Bibarel", "types": [1, 11]}}, {"pk": 91, "model": "pokeapi.pokemon", "fields": {"name": "Gothitelle", "types": [14]}}, {"pk": 92, "model": "pokeapi.pokemon", "fields": {"name": "Squirtle", "types": [11]}}, {"pk": 93, "model": "pokeapi.pokemon", "fields": {"name": "Exploud", "types": [1]}}, {"pk": 94, "model": "pokeapi.pokemon", "fields": {"name": "Skiploom", "types": [3, 12]}}, {"pk": 95, "model": "pokeapi.pokemon", "fields": {"name": "Unfezant", "types": [1, 3]}}, {"pk": 96, "model": "pokeapi.pokemon", "fields": {"name": "Deino", "types": [16, 17]}}, {"pk": 97, "model": "pokeapi.pokemon", "fields": {"name": "Archen", "types": [3, 6]}}, {"pk": 98, "model": "pokeapi.pokemon", "fields": {"name": "Klang", "types": [9]}}, {"pk": 99, "model": "pokeapi.pokemon", "fields": {"name": "Mr", "types": [3, 10]}}, {"pk": 100, "model": "pokeapi.pokemon", "fields": {"name": "Seismitoad", "types": [5, 11]}}, {"pk": 101, "model": "pokeapi.pokemon", "fields": {"name": "Swinub", "types": [5, 15]}}, {"pk": 102, "model": "pokeapi.pokemon", "fields": {"name": "Misdreavus", "types": [8]}}, {"pk": 103, "model": "pokeapi.pokemon", "fields": {"name": "Totodile", "types": [11]}}, {"pk": 104, "model": "pokeapi.pokemon", "fields": {"name": "Maractus", "types": [12]}}, {"pk": 105, "model": "pokeapi.pokemon", "fields": {"name": "Charmander", "types": [10]}}, {"pk": 106, "model": "pokeapi.pokemon", "fields": {"name": "Zebstrika", "types": [13]}}, {"pk": 107, "model": "pokeapi.pokemon", "fields": {"name": "Empoleon", "types": [9, 11]}}, {"pk": 108, "model": "pokeapi.pokemon", "fields": {"name": "Wooper", "types": [5, 11]}}, {"pk": 109, "model": "pokeapi.pokemon", "fields": {"name": "Makuhita", "types": [19]}}, {"pk": 110, "model": "pokeapi.pokemon", "fields": {"name": "Alakazam", "types": [14]}}, {"pk": 111, "model": "pokeapi.pokemon", "fields": {"name": "Dragalge", "types": [4, 16]}}, {"pk": 112, "model": "pokeapi.pokemon", "fields": {"name": "Sunflora", "types": [12]}}, {"pk": 113, "model": "pokeapi.pokemon", "fields": {"name": "Cherrim", "types": [12]}}, {"pk": 114, "model": "pokeapi.pokemon", "fields": {"name": "Seel", "types": [11]}}, {"pk": 115, "model": "pokeapi.pokemon", "fields": {"name": "Carbink", "types": [6, 18]}}, {"pk": 116, "model": "pokeapi.pokemon", "fields": {"name": "Yanma", "types": [3, 7]}}, {"pk": 117, "model": "pokeapi.pokemon", "fields": {"name": "Darmanitan", "types": [10]}}, {"pk": 118, "model": "pokeapi.pokemon", "fields": {"name": "Vanillish", "types": [15]}}, {"pk": 119, "model": "pokeapi.pokemon", "fields": {"name": "Reuniclus", "types": [14]}}, {"pk": 120, "model": "pokeapi.pokemon", "fields": {"name": "Druddigon", "types": [16]}}, {"pk": 121, "model": "pokeapi.pokemon", "fields": {"name": "Snorunt", "types": [15]}}, {"pk": 122, "model": "pokeapi.pokemon", "fields": {"name": "Aipom", "types": [1]}}, {"pk": 123, "model": "pokeapi.pokemon", "fields": {"name": "Breloom", "types": [12, 19]}}, {"pk": 124, "model": "pokeapi.pokemon", "fields": {"name": "Drifblim", "types": [3, 8]}}, {"pk": 125, "model": "pokeapi.pokemon", "fields": {"name": "Goldeen", "types": [11]}}, {"pk": 126, "model": "pokeapi.pokemon", "fields": {"name": "Alomomola", "types": [11]}}, {"pk": 127, "model": "pokeapi.pokemon", "fields": {"name": "Poliwhirl", "types": [11]}}, {"pk": 128, "model": "pokeapi.pokemon", "fields": {"name": "Poliwag", "types": [11]}}, {"pk": 129, "model": "pokeapi.pokemon", "fields": {"name": "Fennekin", "types": [10]}}, {"pk": 130, "model": "pokeapi.pokemon", "fields": {"name": "Kirlia", "types": [14]}}, {"pk": 131, "model": "pokeapi.pokemon", "fields": {"name": "Torkoal", "types": [10]}}, {"pk": 132, "model": "pokeapi.pokemon", "fields": {"name": "Metang", "types": [9, 14]}}, {"pk": 133, "model": "pokeapi.pokemon", "fields": {"name": "Gloom", "types": [4, 12]}}, {"pk": 134, "model": "pokeapi.pokemon", "fields": {"name": "Skiddo", "types": [12]}}, {"pk": 135, "model": "pokeapi.pokemon", "fields": {"name": "Genesect", "types": [7, 9]}}, {"pk": 136, "model": "pokeapi.pokemon", "fields": {"name": "Nidorino", "types": [4]}}, {"pk": 137, "model": "pokeapi.pokemon", "fields": {"name": "Nidorina", "types": [4]}}, {"pk": 138, "model": "pokeapi.pokemon", "fields": {"name": "Regigigas", "types": [1]}}, {"pk": 139, "model": "pokeapi.pokemon", "fields": {"name": "Regice", "types": [15]}}, {"pk": 140, "model": "pokeapi.pokemon", "fields": {"name": "Lickilicky", "types": [1]}}, {"pk": 141, "model": "pokeapi.pokemon", "fields": {"name": "Weepinbell", "types": [4, 12]}}, {"pk": 142, "model": "pokeapi.pokemon", "fields": {"name": "Dodrio", "types": [1, 3]}}, {"pk": 143, "model": "pokeapi.pokemon", "fields": {"name": "Goodra", "types": [16]}}, {"pk": 144, "model": "pokeapi.pokemon", "fields": {"name": "Vespiquen", "types": [3, 7]}}, {"pk": 145, "model": "pokeapi.pokemon", "fields": {"name": "Trapinch", "types": [5]}}, {"pk": 146, "model": "pokeapi.pokemon", "fields": {"name": "Floatzel", "types": [11]}}, {"pk": 147, "model": "pokeapi.pokemon", "fields": {"name": "Electrode", "types": [13]}}, {"pk": 148, "model": "pokeapi.pokemon", "fields": {"name": "Gourgeist", "types": [8, 12]}}, {"pk": 149, "model": "pokeapi.pokemon", "fields": {"name": "Togepi", "types": [1]}}, {"pk": 150, "model": "pokeapi.pokemon", "fields": {"name": "Larvesta", "types": [7, 10]}}, {"pk": 151, "model": "pokeapi.pokemon", "fields": {"name": "Solrock", "types": [6, 14]}}, {"pk": 152, "model": "pokeapi.pokemon", "fields": {"name": "Aegislash", "types": [8, 9]}}, {"pk": 153, "model": "pokeapi.pokemon", "fields": {"name": "Woobat", "types": [3, 14]}}, {"pk": 154, "model": "pokeapi.pokemon", "fields": {"name": "Leavanny", "types": [7, 12]}}, {"pk": 155, "model": "pokeapi.pokemon", "fields": {"name": "Trevenant", "types": [8, 12]}}, {"pk": 156, "model": "pokeapi.pokemon", "fields": {"name": "Sealeo", "types": [11, 15]}}, {"pk": 157, "model": "pokeapi.pokemon", "fields": {"name": "Sceptile", "types": [12]}}, {"pk": 158, "model": "pokeapi.pokemon", "fields": {"name": "Clamperl", "types": [11]}}, {"pk": 159, "model": "pokeapi.pokemon", "fields": {"name": "Octillery", "types": [11]}}, {"pk": 160, "model": "pokeapi.pokemon", "fields": {"name": "Electabuzz", "types": [13]}}, {"pk": 161, "model": "pokeapi.pokemon", "fields": {"name": "Venonat", "types": [4, 7]}}, {"pk": 162, "model": "pokeapi.pokemon", "fields": {"name": "Treecko", "types": [12]}}, {"pk": 163, "model": "pokeapi.pokemon", "fields": {"name": "Pumpkaboo", "types": [8, 12]}}, {"pk": 164, "model": "pokeapi.pokemon", "fields": {"name": "Pikachu", "types": [13]}}, {"pk": 165, "model": "pokeapi.pokemon", "fields": {"name": "Zoroark", "types": [17]}}, {"pk": 166, "model": "pokeapi.pokemon", "fields": {"name": "Jynx", "types": [14, 15]}}, {"pk": 167, "model": "pokeapi.pokemon", "fields": {"name": "Galvantula", "types": [7, 13]}}, {"pk": 168, "model": "pokeapi.pokemon", "fields": {"name": "Manaphy", "types": [11]}}, {"pk": 169, "model": "pokeapi.pokemon", "fields": {"name": "Hitmonchan", "types": [19]}}, {"pk": 170, "model": "pokeapi.pokemon", "fields": {"name": "Fletchling", "types": [1, 3]}}, {"pk": 171, "model": "pokeapi.pokemon", "fields": {"name": "Bunnelby", "types": [1]}}, {"pk": 172, "model": "pokeapi.pokemon", "fields": {"name": "Clefable", "types": [1]}}, {"pk": 173, "model": "pokeapi.pokemon", "fields": {"name": "Cherubi", "types": [12]}}, {"pk": 174, "model": "pokeapi.pokemon", "fields": {"name": "Qwilfish", "types": [4, 11]}}, {"pk": 175, "model": "pokeapi.pokemon", "fields": {"name": "Latios", "types": [14, 16]}}, {"pk": 176, "model": "pokeapi.pokemon", "fields": {"name": "Psyduck", "types": [11]}}, {"pk": 177, "model": "pokeapi.pokemon", "fields": {"name": "Claydol", "types": [5, 14]}}, {"pk": 178, "model": "pokeapi.pokemon", "fields": {"name": "Stunfisk", "types": [5, 13]}}, {"pk": 179, "model": "pokeapi.pokemon", "fields": {"name": "Sudowoodo", "types": [6]}}, {"pk": 180, "model": "pokeapi.pokemon", "fields": {"name": "Starmie", "types": [11, 14]}}, {"pk": 181, "model": "pokeapi.pokemon", "fields": {"name": "Chinchou", "types": [11, 13]}}, {"pk": 182, "model": "pokeapi.pokemon", "fields": {"name": "Steelix", "types": [5, 9]}}, {"pk": 183, "model": "pokeapi.pokemon", "fields": {"name": "Talonflame", "types": [3, 10]}}, {"pk": 184, "model": "pokeapi.pokemon", "fields": {"name": "Phanpy", "types": [5]}}, {"pk": 185, "model": "pokeapi.pokemon", "fields": {"name": "Ninetales", "types": [10]}}, {"pk": 186, "model": "pokeapi.pokemon", "fields": {"name": "Gulpin", "types": [4]}}, {"pk": 187, "model": "pokeapi.pokemon", "fields": {"name": "Azumarill", "types": [11]}}, {"pk": 188, "model": "pokeapi.pokemon", "fields": {"name": "Glalie", "types": [15]}}, {"pk": 189, "model": "pokeapi.pokemon", "fields": {"name": "Camerupt", "types": [5, 10]}}, {"pk": 190, "model": "pokeapi.pokemon", "fields": {"name": "Jirachi", "types": [9, 14]}}, {"pk": 191, "model": "pokeapi.pokemon", "fields": {"name": "Hydreigon", "types": [16, 17]}}, {"pk": 192, "model": "pokeapi.pokemon", "fields": {"name": "Wingull", "types": [3, 11]}}, {"pk": 193, "model": "pokeapi.pokemon", "fields": {"name": "Farfetch", "types": [3, 10]}}, {"pk": 194, "model": "pokeapi.pokemon", "fields": {"name": "Gallade", "types": [14, 19]}}, {"pk": 195, "model": "pokeapi.pokemon", "fields": {"name": "Prinplup", "types": [11]}}, {"pk": 196, "model": "pokeapi.pokemon", "fields": {"name": "Weezing", "types": [4]}}, {"pk": 197, "model": "pokeapi.pokemon", "fields": {"name": "Swoobat", "types": [3, 14]}}, {"pk": 198, "model": "pokeapi.pokemon", "fields": {"name": "Mareep", "types": [13]}}, {"pk": 199, "model": "pokeapi.pokemon", "fields": {"name": "Spiritomb", "types": [8, 17]}}, {"pk": 200, "model": "pokeapi.pokemon", "fields": {"name": "Reshiram", "types": [10, 16]}}, {"pk": 201, "model": "pokeapi.pokemon", "fields": {"name": "Paras", "types": [7, 12]}}, {"pk": 202, "model": "pokeapi.pokemon", "fields": {"name": "Liepard", "types": [17]}}, {"pk": 203, "model": "pokeapi.pokemon", "fields": {"name": "Pidove", "types": [1, 3]}}, {"pk": 204, "model": "pokeapi.pokemon", "fields": {"name": "Sandslash", "types": [5]}}, {"pk": 205, "model": "pokeapi.pokemon", "fields": {"name": "Kangaskhan", "types": [1]}}, {"pk": 206, "model": "pokeapi.pokemon", "fields": {"name": "Tropius", "types": [3, 12]}}, {"pk": 207, "model": "pokeapi.pokemon", "fields": {"name": "Aron", "types": [6, 9]}}, {"pk": 208, "model": "pokeapi.pokemon", "fields": {"name": "Machamp", "types": [19]}}, {"pk": 209, "model": "pokeapi.pokemon", "fields": {"name": "Tympole", "types": [11]}}, {"pk": 210, "model": "pokeapi.pokemon", "fields": {"name": "Grotle", "types": [12]}}, {"pk": 211, "model": "pokeapi.pokemon", "fields": {"name": "Omanyte", "types": [6, 11]}}, {"pk": 212, "model": "pokeapi.pokemon", "fields": {"name": "Slowpoke", "types": [11, 14]}}, {"pk": 213, "model": "pokeapi.pokemon", "fields": {"name": "Horsea", "types": [11]}}, {"pk": 214, "model": "pokeapi.pokemon", "fields": {"name": "Gligar", "types": [3, 5]}}, {"pk": 215, "model": "pokeapi.pokemon", "fields": {"name": "Exeggutor", "types": [12, 14]}}, {"pk": 216, "model": "pokeapi.pokemon", "fields": {"name": "Barboach", "types": [5, 11]}}, {"pk": 217, "model": "pokeapi.pokemon", "fields": {"name": "Parasect", "types": [7, 12]}}, {"pk": 218, "model": "pokeapi.pokemon", "fields": {"name": "Cobalion", "types": [9, 19]}}, {"pk": 219, "model": "pokeapi.pokemon", "fields": {"name": "Minun", "types": [13]}}, {"pk": 220, "model": "pokeapi.pokemon", "fields": {"name": "Budew", "types": [4, 12]}}, {"pk": 221, "model": "pokeapi.pokemon", "fields": {"name": "Ditto", "types": [1]}}, {"pk": 222, "model": "pokeapi.pokemon", "fields": {"name": "Eelektross", "types": [13]}}, {"pk": 223, "model": "pokeapi.pokemon", "fields": {"name": "Mudkip", "types": [11]}}, {"pk": 224, "model": "pokeapi.pokemon", "fields": {"name": "Mantyke", "types": [3, 11]}}, {"pk": 225, "model": "pokeapi.pokemon", "fields": {"name": "Mesprit", "types": [14]}}, {"pk": 226, "model": "pokeapi.pokemon", "fields": {"name": "Bisharp", "types": [9, 17]}}, {"pk": 227, "model": "pokeapi.pokemon", "fields": {"name": "Zangoose", "types": [1]}}, {"pk": 228, "model": "pokeapi.pokemon", "fields": {"name": "Kyurem", "types": [15, 16]}}, {"pk": 229, "model": "pokeapi.pokemon", "fields": {"name": "Sigilyph", "types": [3, 14]}}, {"pk": 230, "model": "pokeapi.pokemon", "fields": {"name": "Groudon", "types": [5]}}, {"pk": 231, "model": "pokeapi.pokemon", "fields": {"name": "Florges", "types": [18]}}, {"pk": 232, "model": "pokeapi.pokemon", "fields": {"name": "Nidoqueen", "types": [4, 5]}}, {"pk": 233, "model": "pokeapi.pokemon", "fields": {"name": "Altaria", "types": [3, 16]}}, {"pk": 234, "model": "pokeapi.pokemon", "fields": {"name": "Lotad", "types": [11, 12]}}, {"pk": 235, "model": "pokeapi.pokemon", "fields": {"name": "Deoxys", "types": [14]}}, {"pk": 236, "model": "pokeapi.pokemon", "fields": {"name": "Meloetta", "types": [1, 14]}}, {"pk": 237, "model": "pokeapi.pokemon", "fields": {"name": "Togekiss", "types": [1, 3]}}, {"pk": 238, "model": "pokeapi.pokemon", "fields": {"name": "Luxio", "types": [13]}}, {"pk": 239, "model": "pokeapi.pokemon", "fields": {"name": "Wormadam", "types": [7, 12]}}, {"pk": 240, "model": "pokeapi.pokemon", "fields": {"name": "Venusaur", "types": [4, 12]}}, {"pk": 241, "model": "pokeapi.pokemon", "fields": {"name": "Tepig", "types": [10]}}, {"pk": 242, "model": "pokeapi.pokemon", "fields": {"name": "Blastoise", "types": [11]}}, {"pk": 243, "model": "pokeapi.pokemon", "fields": {"name": "Cubchoo", "types": [15]}}, {"pk": 244, "model": "pokeapi.pokemon", "fields": {"name": "Pachirisu", "types": [13]}}, {"pk": 245, "model": "pokeapi.pokemon", "fields": {"name": "Klefki", "types": [9, 18]}}, {"pk": 246, "model": "pokeapi.pokemon", "fields": {"name": "Marill", "types": [11, 18]}}, {"pk": 247, "model": "pokeapi.pokemon", "fields": {"name": "Piplup", "types": [11]}}, {"pk": 248, "model": "pokeapi.pokemon", "fields": {"name": "Bulbasaur", "types": [4, 12]}}, {"pk": 249, "model": "pokeapi.pokemon", "fields": {"name": "Jigglypuff", "types": [1, 18]}}, {"pk": 250, "model": "pokeapi.pokemon", "fields": {"name": "Cascoon", "types": [7]}}, {"pk": 251, "model": "pokeapi.pokemon", "fields": {"name": "Abra", "types": [14]}}, {"pk": 252, "model": "pokeapi.pokemon", "fields": {"name": "Ralts", "types": [14]}}, {"pk": 253, "model": "pokeapi.pokemon", "fields": {"name": "Kecleon", "types": [1]}}, {"pk": 254, "model": "pokeapi.pokemon", "fields": {"name": "Boldore", "types": [6]}}, {"pk": 255, "model": "pokeapi.pokemon", "fields": {"name": "Marshtomp", "types": [5, 11]}}, {"pk": 256, "model": "pokeapi.pokemon", "fields": {"name": "Throh", "types": [19]}}, {"pk": 257, "model": "pokeapi.pokemon", "fields": {"name": "Wartortle", "types": [11]}}, {"pk": 258, "model": "pokeapi.pokemon", "fields": {"name": "Ferroseed", "types": [9, 12]}}, {"pk": 259, "model": "pokeapi.pokemon", "fields": {"name": "Pignite", "types": [10, 19]}}, {"pk": 260, "model": "pokeapi.pokemon", "fields": {"name": "Deerling", "types": [1, 12]}}, {"pk": 261, "model": "pokeapi.pokemon", "fields": {"name": "Magikarp", "types": [11]}}, {"pk": 262, "model": "pokeapi.pokemon", "fields": {"name": "Pawniard", "types": [9, 17]}}, {"pk": 263, "model": "pokeapi.pokemon", "fields": {"name": "Dusknoir", "types": [8]}}, {"pk": 264, "model": "pokeapi.pokemon", "fields": {"name": "Skrelp", "types": [4, 11]}}, {"pk": 265, "model": "pokeapi.pokemon", "fields": {"name": "Baltoy", "types": [5, 14]}}, {"pk": 266, "model": "pokeapi.pokemon", "fields": {"name": "Taillow", "types": [1, 3]}}, {"pk": 267, "model": "pokeapi.pokemon", "fields": {"name": "Pidgeotto", "types": [1, 3]}}, {"pk": 268, "model": "pokeapi.pokemon", "fields": {"name": "Rattata", "types": [1]}}, {"pk": 269, "model": "pokeapi.pokemon", "fields": {"name": "Girafarig", "types": [1, 14]}}, {"pk": 270, "model": "pokeapi.pokemon", "fields": {"name": "Granbull", "types": [1]}}, {"pk": 271, "model": "pokeapi.pokemon", "fields": {"name": "Electrike", "types": [13]}}, {"pk": 272, "model": "pokeapi.pokemon", "fields": {"name": "Venipede", "types": [4, 7]}}, {"pk": 273, "model": "pokeapi.pokemon", "fields": {"name": "Vulpix", "types": [10]}}, {"pk": 274, "model": "pokeapi.pokemon", "fields": {"name": "Sylveon", "types": [18]}}, {"pk": 275, "model": "pokeapi.pokemon", "fields": {"name": "Gardevoir", "types": [14, 18]}}, {"pk": 276, "model": "pokeapi.pokemon", "fields": {"name": "Bellsprout", "types": [4, 12]}}, {"pk": 277, "model": "pokeapi.pokemon", "fields": {"name": "Tangrowth", "types": [12]}}, {"pk": 278, "model": "pokeapi.pokemon", "fields": {"name": "Dedenne", "types": [13, 18]}}, {"pk": 279, "model": "pokeapi.pokemon", "fields": {"name": "Nosepass", "types": [6]}}, {"pk": 280, "model": "pokeapi.pokemon", "fields": {"name": "Slaking", "types": [1]}}, {"pk": 281, "model": "pokeapi.pokemon", "fields": {"name": "Spearow", "types": [1, 3]}}, {"pk": 282, "model": "pokeapi.pokemon", "fields": {"name": "Chikorita", "types": [12]}}, {"pk": 283, "model": "pokeapi.pokemon", "fields": {"name": "Scyther", "types": [3, 7]}}, {"pk": 284, "model": "pokeapi.pokemon", "fields": {"name": "Honchkrow", "types": [3, 17]}}, {"pk": 285, "model": "pokeapi.pokemon", "fields": {"name": "Eelektrik", "types": [13]}}, {"pk": 286, "model": "pokeapi.pokemon", "fields": {"name": "Togetic", "types": [1, 3]}}, {"pk": 287, "model": "pokeapi.pokemon", "fields": {"name": "Sewaddle", "types": [7, 12]}}, {"pk": 288, "model": "pokeapi.pokemon", "fields": {"name": "Vigoroth", "types": [1]}}, {"pk": 289, "model": "pokeapi.pokemon", "fields": {"name": "Houndoom", "types": [10, 17]}}, {"pk": 290, "model": "pokeapi.pokemon", "fields": {"name": "Quagsire", "types": [5, 11]}}, {"pk": 291, "model": "pokeapi.pokemon", "fields": {"name": "Duskull", "types": [8]}}, {"pk": 292, "model": "pokeapi.pokemon", "fields": {"name": "Masquerain", "types": [3, 7]}}, {"pk": 293, "model": "pokeapi.pokemon", "fields": {"name": "Luvdisc", "types": [11]}}, {"pk": 294, "model": "pokeapi.pokemon", "fields": {"name": "Phantump", "types": [8, 12]}}, {"pk": 295, "model": "pokeapi.pokemon", "fields": {"name": "Gyarados", "types": [3, 11]}}, {"pk": 296, "model": "pokeapi.pokemon", "fields": {"name": "Axew", "types": [16]}}, {"pk": 297, "model": "pokeapi.pokemon", "fields": {"name": "Metapod", "types": [7]}}, {"pk": 298, "model": "pokeapi.pokemon", "fields": {"name": "Spheal", "types": [11, 15]}}, {"pk": 299, "model": "pokeapi.pokemon", "fields": {"name": "Bayleef", "types": [12]}}, {"pk": 300, "model": "pokeapi.pokemon", "fields": {"name": "Wailord", "types": [11]}}, {"pk": 301, "model": "pokeapi.pokemon", "fields": {"name": "Heatran", "types": [9, 10]}}, {"pk": 302, "model": "pokeapi.pokemon", "fields": {"name": "Ponyta", "types": [10]}}, {"pk": 303, "model": "pokeapi.pokemon", "fields": {"name": "Wailmer", "types": [11]}}, {"pk": 304, "model": "pokeapi.pokemon", "fields": {"name": "Quilava", "types": [10]}}, {"pk": 305, "model": "pokeapi.pokemon", "fields": {"name": "Pangoro", "types": [17, 19]}}, {"pk": 306, "model": "pokeapi.pokemon", "fields": {"name": "Hariyama", "types": [19]}}, {"pk": 307, "model": "pokeapi.pokemon", "fields": {"name": "Ivysaur", "types": [4, 12]}}, {"pk": 308, "model": "pokeapi.pokemon", "fields": {"name": "Chingling", "types": [14]}}, {"pk": 309, "model": "pokeapi.pokemon", "fields": {"name": "Magcargo", "types": [6, 10]}}, {"pk": 310, "model": "pokeapi.pokemon", "fields": {"name": "Whiscash", "types": [5, 11]}}, {"pk": 311, "model": "pokeapi.pokemon", "fields": {"name": "Vileplume", "types": [4, 12]}}, {"pk": 312, "model": "pokeapi.pokemon", "fields": {"name": "Slowking", "types": [11, 14]}}, {"pk": 313, "model": "pokeapi.pokemon", "fields": {"name": "Dustox", "types": [4, 7]}}, {"pk": 314, "model": "pokeapi.pokemon", "fields": {"name": "Lopunny", "types": [1]}}, {"pk": 315, "model": "pokeapi.pokemon", "fields": {"name": "Hawlucha", "types": [3, 19]}}, {"pk": 316, "model": "pokeapi.pokemon", "fields": {"name": "Beldum", "types": [9, 14]}}, {"pk": 317, "model": "pokeapi.pokemon", "fields": {"name": "Bastiodon", "types": [6, 9]}}, {"pk": 318, "model": "pokeapi.pokemon", "fields": {"name": "Sandshrew", "types": [5]}}, {"pk": 319, "model": "pokeapi.pokemon", "fields": {"name": "Braviary", "types": [1, 3]}}, {"pk": 320, "model": "pokeapi.pokemon", "fields": {"name": "Shroomish", "types": [12]}}, {"pk": 321, "model": "pokeapi.pokemon", "fields": {"name": "Spoink", "types": [14]}}, {"pk": 322, "model": "pokeapi.pokemon", "fields": {"name": "Vanilluxe", "types": [15]}}, {"pk": 323, "model": "pokeapi.pokemon", "fields": {"name": "Furret", "types": [1]}}, {"pk": 324, "model": "pokeapi.pokemon", "fields": {"name": "Whimsicott", "types": [12]}}, {"pk": 325, "model": "pokeapi.pokemon", "fields": {"name": "Larvitar", "types": [5, 6]}}, {"pk": 326, "model": "pokeapi.pokemon", "fields": {"name": "Medicham", "types": [14, 19]}}, {"pk": 327, "model": "pokeapi.pokemon", "fields": {"name": "Furfrou", "types": [1]}}, {"pk": 328, "model": "pokeapi.pokemon", "fields": {"name": "Golbat", "types": [3, 4]}}, {"pk": 329, "model": "pokeapi.pokemon", "fields": {"name": "Gengar", "types": [4, 8]}}, {"pk": 330, "model": "pokeapi.pokemon", "fields": {"name": "Chimecho", "types": [14]}}, {"pk": 331, "model": "pokeapi.pokemon", "fields": {"name": "Pyroar", "types": [1, 10]}}, {"pk": 332, "model": "pokeapi.pokemon", "fields": {"name": "Blitzle", "types": [13]}}, {"pk": 333, "model": "pokeapi.pokemon", "fields": {"name": "Carvanha", "types": [11, 17]}}, {"pk": 334, "model": "pokeapi.pokemon", "fields": {"name": "Lumineon", "types": [11]}}, {"pk": 335, "model": "pokeapi.pokemon", "fields": {"name": "Piloswine", "types": [5, 15]}}, {"pk": 336, "model": "pokeapi.pokemon", "fields": {"name": "Lickitung", "types": [1]}}, {"pk": 337, "model": "pokeapi.pokemon", "fields": {"name": "Venomoth", "types": [4, 7]}}, {"pk": 338, "model": "pokeapi.pokemon", "fields": {"name": "Finneon", "types": [11]}}, {"pk": 339, "model": "pokeapi.pokemon", "fields": {"name": "Elgyem", "types": [14]}}, {"pk": 340, "model": "pokeapi.pokemon", "fields": {"name": "Pichu", "types": [13]}}, {"pk": 341, "model": "pokeapi.pokemon", "fields": {"name": "Crustle", "types": [6, 7]}}, {"pk": 342, "model": "pokeapi.pokemon", "fields": {"name": "Weavile", "types": [15, 17]}}, {"pk": 343, "model": "pokeapi.pokemon", "fields": {"name": "Gothita", "types": [14]}}, {"pk": 344, "model": "pokeapi.pokemon", "fields": {"name": "Magby", "types": [10]}}, {"pk": 345, "model": "pokeapi.pokemon", "fields": {"name": "Smeargle", "types": [1]}}, {"pk": 346, "model": "pokeapi.pokemon", "fields": {"name": "Carracosta", "types": [6, 11]}}, {"pk": 347, "model": "pokeapi.pokemon", "fields": {"name": "Gigalith", "types": [6]}}, {"pk": 348, "model": "pokeapi.pokemon", "fields": {"name": "Keldeo", "types": [11, 19]}}, {"pk": 349, "model": "pokeapi.pokemon", "fields": {"name": "Manectric", "types": [13]}}, {"pk": 350, "model": "pokeapi.pokemon", "fields": {"name": "Illumise", "types": [7]}}, {"pk": 351, "model": "pokeapi.pokemon", "fields": {"name": "Chatot", "types": [1, 3]}}, {"pk": 352, "model": "pokeapi.pokemon", "fields": {"name": "Xatu", "types": [3, 14]}}, {"pk": 353, "model": "pokeapi.pokemon", "fields": {"name": "Scraggy", "types": [17, 19]}}, {"pk": 354, "model": "pokeapi.pokemon", "fields": {"name": "Poochyena", "types": [17]}}, {"pk": 355, "model": "pokeapi.pokemon", "fields": {"name": "Azelf", "types": [14]}}, {"pk": 356, "model": "pokeapi.pokemon", "fields": {"name": "Virizion", "types": [12, 19]}}, {"pk": 357, "model": "pokeapi.pokemon", "fields": {"name": "Floette", "types": [18]}}, {"pk": 358, "model": "pokeapi.pokemon", "fields": {"name": "Shuckle", "types": [6, 7]}}, {"pk": 359, "model": "pokeapi.pokemon", "fields": {"name": "Kakuna", "types": [4, 7]}}, {"pk": 360, "model": "pokeapi.pokemon", "fields": {"name": "Seaking", "types": [11]}}, {"pk": 361, "model": "pokeapi.pokemon", "fields": {"name": "Buizel", "types": [11]}}, {"pk": 362, "model": "pokeapi.pokemon", "fields": {"name": "Clawitzer", "types": [11]}}, {"pk": 363, "model": "pokeapi.pokemon", "fields": {"name": "Cyndaquil", "types": [10]}}, {"pk": 364, "model": "pokeapi.pokemon", "fields": {"name": "Malamar", "types": [14, 17]}}, {"pk": 365, "model": "pokeapi.pokemon", "fields": {"name": "Staravia", "types": [1, 3]}}, {"pk": 366, "model": "pokeapi.pokemon", "fields": {"name": "Entei", "types": [10]}}, {"pk": 367, "model": "pokeapi.pokemon", "fields": {"name": "Magnezone", "types": [9, 13]}}, {"pk": 368, "model": "pokeapi.pokemon", "fields": {"name": "Staryu", "types": [11]}}, {"pk": 369, "model": "pokeapi.pokemon", "fields": {"name": "Beheeyem", "types": [14]}}, {"pk": 370, "model": "pokeapi.pokemon", "fields": {"name": "Dunsparce", "types": [1]}}, {"pk": 371, "model": "pokeapi.pokemon", "fields": {"name": "Murkrow", "types": [3, 17]}}, {"pk": 372, "model": "pokeapi.pokemon", "fields": {"name": "Braixen", "types": [10]}}, {"pk": 373, "model": "pokeapi.pokemon", "fields": {"name": "Spewpa", "types": [7]}}, {"pk": 374, "model": "pokeapi.pokemon", "fields": {"name": "Dusclops", "types": [8]}}, {"pk": 375, "model": "pokeapi.pokemon", "fields": {"name": "Ariados", "types": [4, 7]}}, {"pk": 376, "model": "pokeapi.pokemon", "fields": {"name": "Foongus", "types": [4, 12]}}, {"pk": 377, "model": "pokeapi.pokemon", "fields": {"name": "Vullaby", "types": [3, 17]}}, {"pk": 378, "model": "pokeapi.pokemon", "fields": {"name": "Yanmega", "types": [3, 7]}}, {"pk": 379, "model": "pokeapi.pokemon", "fields": {"name": "Simisage", "types": [12]}}, {"pk": 380, "model": "pokeapi.pokemon", "fields": {"name": "Burmy", "types": [7]}}, {"pk": 381, "model": "pokeapi.pokemon", "fields": {"name": "Silcoon", "types": [7]}}, {"pk": 382, "model": "pokeapi.pokemon", "fields": {"name": "Lombre", "types": [11, 12]}}, {"pk": 383, "model": "pokeapi.pokemon", "fields": {"name": "Volcarona", "types": [7, 10]}}, {"pk": 384, "model": "pokeapi.pokemon", "fields": {"name": "Arceus", "types": [1]}}, {"pk": 385, "model": "pokeapi.pokemon", "fields": {"name": "Corsola", "types": [6, 11]}}, {"pk": 386, "model": "pokeapi.pokemon", "fields": {"name": "Unown", "types": [14]}}, {"pk": 387, "model": "pokeapi.pokemon", "fields": {"name": "Frillish", "types": [8, 11]}}, {"pk": 388, "model": "pokeapi.pokemon", "fields": {"name": "Kadabra", "types": [14]}}, {"pk": 389, "model": "pokeapi.pokemon", "fields": {"name": "Oddish", "types": [4, 12]}}, {"pk": 390, "model": "pokeapi.pokemon", "fields": {"name": "Uxie", "types": [14]}}, {"pk": 391, "model": "pokeapi.pokemon", "fields": {"name": "Beedrill", "types": [4, 7]}}, {"pk": 392, "model": "pokeapi.pokemon", "fields": {"name": "Ambipom", "types": [1]}}, {"pk": 393, "model": "pokeapi.pokemon", "fields": {"name": "Hitmonlee", "types": [19]}}, {"pk": 394, "model": "pokeapi.pokemon", "fields": {"name": "Gorebyss", "types": [11]}}, {"pk": 395, "model": "pokeapi.pokemon", "fields": {"name": "Lampent", "types": [8, 10]}}, {"pk": 396, "model": "pokeapi.pokemon", "fields": {"name": "Cacturne", "types": [12, 17]}}, {"pk": 397, "model": "pokeapi.pokemon", "fields": {"name": "Raichu", "types": [13]}}, {"pk": 398, "model": "pokeapi.pokemon", "fields": {"name": "Musharna", "types": [14]}}, {"pk": 399, "model": "pokeapi.pokemon", "fields": {"name": "Emboar", "types": [10, 19]}}, {"pk": 400, "model": "pokeapi.pokemon", "fields": {"name": "Blaziken", "types": [10, 19]}}, {"pk": 401, "model": "pokeapi.pokemon", "fields": {"name": "Rhydon", "types": [5, 6]}}, {"pk": 402, "model": "pokeapi.pokemon", "fields": {"name": "Nolbat", "types": [3, 16]}}, {"pk": 403, "model": "pokeapi.pokemon", "fields": {"name": "Heatmor", "types": [10]}}, {"pk": 404, "model": "pokeapi.pokemon", "fields": {"name": "Farfetch'd", "types": [1, 3]}}, {"pk": 405, "model": "pokeapi.pokemon", "fields": {"name": "Slurpuff", "types": [18]}}, {"pk": 406, "model": "pokeapi.pokemon", "fields": {"name": "Ferrothorn", "types": [9, 12]}}, {"pk": 407, "model": "pokeapi.pokemon", "fields": {"name": "Sunkern", "types": [12]}}, {"pk": 408, "model": "pokeapi.pokemon", "fields": {"name": "Milotic", "types": [11]}}, {"pk": 409, "model": "pokeapi.pokemon", "fields": {"name": "Aerodactyl", "types": [3, 6]}}, {"pk": 410, "model": "pokeapi.pokemon", "fields": {"name": "Koffing", "types": [4]}}, {"pk": 411, "model": "pokeapi.pokemon", "fields": {"name": "Plusle", "types": [13]}}, {"pk": 412, "model": "pokeapi.pokemon", "fields": {"name": "Shellder", "types": [11]}}, {"pk": 413, "model": "pokeapi.pokemon", "fields": {"name": "Mr Mime", "types": [14]}}, {"pk": 414, "model": "pokeapi.pokemon", "fields": {"name": "Dratini", "types": [16]}}, {"pk": 415, "model": "pokeapi.pokemon", "fields": {"name": "Starly", "types": [1, 3]}}, {"pk": 416, "model": "pokeapi.pokemon", "fields": {"name": "Aurorus", "types": [6, 15]}}, {"pk": 417, "model": "pokeapi.pokemon", "fields": {"name": "Mantine", "types": [3, 11]}}, {"pk": 418, "model": "pokeapi.pokemon", "fields": {"name": "Pineco", "types": [7]}}, {"pk": 419, "model": "pokeapi.pokemon", "fields": {"name": "Lairon", "types": [6, 9]}}, {"pk": 420, "model": "pokeapi.pokemon", "fields": {"name": "Doublade", "types": [8, 9]}}, {"pk": 421, "model": "pokeapi.pokemon", "fields": {"name": "Shellos", "types": [11]}}, {"pk": 422, "model": "pokeapi.pokemon", "fields": {"name": "Bonsly", "types": [6]}}, {"pk": 423, "model": "pokeapi.pokemon", "fields": {"name": "Leafeon", "types": [12]}}, {"pk": 424, "model": "pokeapi.pokemon", "fields": {"name": "Corphish", "types": [11]}}, {"pk": 425, "model": "pokeapi.pokemon", "fields": {"name": "Arcanine", "types": [10]}}, {"pk": 426, "model": "pokeapi.pokemon", "fields": {"name": "Hippopotas", "types": [5]}}, {"pk": 427, "model": "pokeapi.pokemon", "fields": {"name": "Igglybuff", "types": [1]}}, {"pk": 428, "model": "pokeapi.pokemon", "fields": {"name": "Noctowl", "types": [1, 3]}}, {"pk": 429, "model": "pokeapi.pokemon", "fields": {"name": "Cofagrigus", "types": [8]}}, {"pk": 430, "model": "pokeapi.pokemon", "fields": {"name": "Snorlax", "types": [1]}}, {"pk": 431, "model": "pokeapi.pokemon", "fields": {"name": "Articuno", "types": [3, 15]}}, {"pk": 432, "model": "pokeapi.pokemon", "fields": {"name": "Roselia", "types": [4, 12]}}, {"pk": 433, "model": "pokeapi.pokemon", "fields": {"name": "Rhyperior", "types": [5, 6]}}, {"pk": 434, "model": "pokeapi.pokemon", "fields": {"name": "Golem", "types": [5, 6]}}, {"pk": 435, "model": "pokeapi.pokemon", "fields": {"name": "Pinsir", "types": [7]}}, {"pk": 436, "model": "pokeapi.pokemon", "fields": {"name": "Meowstic", "types": [14]}}, {"pk": 437, "model": "pokeapi.pokemon", "fields": {"name": "Banette", "types": [8]}}, {"pk": 438, "model": "pokeapi.pokemon", "fields": {"name": "Whirlipede", "types": [4, 7]}}, {"pk": 439, "model": "pokeapi.pokemon", "fields": {"name": "Servine", "types": [12]}}, {"pk": 440, "model": "pokeapi.pokemon", "fields": {"name": "Inkay", "types": [14, 17]}}, {"pk": 441, "model": "pokeapi.pokemon", "fields": {"name": "Tauros", "types": [1]}}, {"pk": 442, "model": "pokeapi.pokemon", "fields": {"name": "Suicune", "types": [11]}}, {"pk": 443, "model": "pokeapi.pokemon", "fields": {"name": "Shelgon", "types": [16]}}, {"pk": 444, "model": "pokeapi.pokemon", "fields": {"name": "Raikou", "types": [13]}}, {"pk": 445, "model": "pokeapi.pokemon", "fields": {"name": "Greninja", "types": [11, 17]}}, {"pk": 446, "model": "pokeapi.pokemon", "fields": {"name": "Arbok", "types": [4]}}, {"pk": 447, "model": "pokeapi.pokemon", "fields": {"name": "Vivillon", "types": [3, 7]}}, {"pk": 448, "model": "pokeapi.pokemon", "fields": {"name": "Porygon2", "types": [1]}}, {"pk": 449, "model": "pokeapi.pokemon", "fields": {"name": "Mamoswine", "types": [5, 15]}}, {"pk": 450, "model": "pokeapi.pokemon", "fields": {"name": "Trubbish", "types": [4]}}, {"pk": 451, "model": "pokeapi.pokemon", "fields": {"name": "Chansey", "types": [1]}}, {"pk": 452, "model": "pokeapi.pokemon", "fields": {"name": "Clauncher", "types": [11]}}, {"pk": 453, "model": "pokeapi.pokemon", "fields": {"name": "Infernape", "types": [10, 19]}}, {"pk": 454, "model": "pokeapi.pokemon", "fields": {"name": "Geodude", "types": [5, 6]}}, {"pk": 455, "model": "pokeapi.pokemon", "fields": {"name": "Mismagius", "types": [8]}}, {"pk": 456, "model": "pokeapi.pokemon", "fields": {"name": "Slugma", "types": [10]}}, {"pk": 457, "model": "pokeapi.pokemon", "fields": {"name": "Croagunk", "types": [4, 19]}}, {"pk": 458, "model": "pokeapi.pokemon", "fields": {"name": "Primeape", "types": [19]}}, {"pk": 459, "model": "pokeapi.pokemon", "fields": {"name": "Hoothoot", "types": [1, 3]}}, {"pk": 460, "model": "pokeapi.pokemon", "fields": {"name": "Relicanth", "types": [6, 11]}}, {"pk": 461, "model": "pokeapi.pokemon", "fields": {"name": "Tyrogue", "types": [19]}}, {"pk": 462, "model": "pokeapi.pokemon", "fields": {"name": "Sawsbuck", "types": [1, 12]}}, {"pk": 463, "model": "pokeapi.pokemon", "fields": {"name": "Dialga", "types": [9, 16]}}, {"pk": 464, "model": "pokeapi.pokemon", "fields": {"name": "Nidoran", "types": [4]}}, {"pk": 465, "model": "pokeapi.pokemon", "fields": {"name": "Amoonguss", "types": [4, 12]}}, {"pk": 466, "model": "pokeapi.pokemon", "fields": {"name": "Jolteon", "types": [13]}}, {"pk": 467, "model": "pokeapi.pokemon", "fields": {"name": "Swablu", "types": [1, 3]}}, {"pk": 468, "model": "pokeapi.pokemon", "fields": {"name": "Kricketot", "types": [7]}}, {"pk": 469, "model": "pokeapi.pokemon", "fields": {"name": "Golduck", "types": [11]}}, {"pk": 470, "model": "pokeapi.pokemon", "fields": {"name": "Chimchar", "types": [10]}}, {"pk": 471, "model": "pokeapi.pokemon", "fields": {"name": "Chesnaught", "types": [12, 19]}}, {"pk": 472, "model": "pokeapi.pokemon", "fields": {"name": "Sandile", "types": [5, 17]}}, {"pk": 473, "model": "pokeapi.pokemon", "fields": {"name": "Zubat", "types": [3, 4]}}, {"pk": 474, "model": "pokeapi.pokemon", "fields": {"name": "Politoed", "types": [11]}}, {"pk": 475, "model": "pokeapi.pokemon", "fields": {"name": "Gible", "types": [5, 16]}}, {"pk": 476, "model": "pokeapi.pokemon", "fields": {"name": "Ekans", "types": [4]}}, {"pk": 477, "model": "pokeapi.pokemon", "fields": {"name": "Umbreon", "types": [17]}}, {"pk": 478, "model": "pokeapi.pokemon", "fields": {"name": "Flaaffy", "types": [13]}}, {"pk": 479, "model": "pokeapi.pokemon", "fields": {"name": "Heracross", "types": [7, 19]}}, {"pk": 480, "model": "pokeapi.pokemon", "fields": {"name": "Feraligatr", "types": [11]}}, {"pk": 481, "model": "pokeapi.pokemon", "fields": {"name": "Toxicroak", "types": [4, 19]}}, {"pk": 482, "model": "pokeapi.pokemon", "fields": {"name": "Voltorb", "types": [13]}}, {"pk": 483, "model": "pokeapi.pokemon", "fields": {"name": "Panpour", "types": [11]}}, {"pk": 484, "model": "pokeapi.pokemon", "fields": {"name": "Cottonee", "types": [12]}}, {"pk": 485, "model": "pokeapi.pokemon", "fields": {"name": "Dragonite", "types": [3, 16]}}, {"pk": 486, "model": "pokeapi.pokemon", "fields": {"name": "Remoraid", "types": [11]}}, {"pk": 487, "model": "pokeapi.pokemon", "fields": {"name": "Dewott", "types": []}}, {"pk": 488, "model": "pokeapi.pokemon", "fields": {"name": "Vaporeon", "types": [11]}}, {"pk": 489, "model": "pokeapi.pokemon", "fields": {"name": "Swadloon", "types": [7, 12]}}, {"pk": 490, "model": "pokeapi.pokemon", "fields": {"name": "Diglett", "types": [5]}}, {"pk": 491, "model": "pokeapi.pokemon", "fields": {"name": "Smoochum", "types": [14, 15]}}, {"pk": 492, "model": "pokeapi.pokemon", "fields": {"name": "Klinklang", "types": [9]}}, {"pk": 493, "model": "pokeapi.pokemon", "fields": {"name": "Terrakion", "types": [6, 19]}}, {"pk": 494, "model": "pokeapi.pokemon", "fields": {"name": "Conkeldurr", "types": [19]}}, {"pk": 495, "model": "pokeapi.pokemon", "fields": {"name": "Gastly", "types": [4, 8]}}, {"pk": 496, "model": "pokeapi.pokemon", "fields": {"name": "Mothim", "types": [3, 7]}}, {"pk": 497, "model": "pokeapi.pokemon", "fields": {"name": "Teddiursa", "types": [1]}}, {"pk": 498, "model": "pokeapi.pokemon", "fields": {"name": "Hypno", "types": [14]}}, {"pk": 499, "model": "pokeapi.pokemon", "fields": {"name": "Machoke", "types": [19]}}, {"pk": 500, "model": "pokeapi.pokemon", "fields": {"name": "Porygon", "types": [1]}}, {"pk": 501, "model": "pokeapi.pokemon", "fields": {"name": "Audino", "types": [1]}}, {"pk": 502, "model": "pokeapi.pokemon", "fields": {"name": "Jumpluff", "types": [3, 12]}}, {"pk": 503, "model": "pokeapi.pokemon", "fields": {"name": "Drifloon", "types": [3, 8]}}, {"pk": 504, "model": "pokeapi.pokemon", "fields": {"name": "Drapion", "types": [4, 17]}}, {"pk": 505, "model": "pokeapi.pokemon", "fields": {"name": "Probopass", "types": [6, 9]}}, {"pk": 506, "model": "pokeapi.pokemon", "fields": {"name": "Excadrill", "types": [5, 9]}}, {"pk": 507, "model": "pokeapi.pokemon", "fields": {"name": "Solosis", "types": [14]}}, {"pk": 508, "model": "pokeapi.pokemon", "fields": {"name": "Gurdurr", "types": [19]}}, {"pk": 509, "model": "pokeapi.pokemon", "fields": {"name": "Timburr", "types": [19]}}, {"pk": 510, "model": "pokeapi.pokemon", "fields": {"name": "Sawk", "types": [19]}}, {"pk": 511, "model": "pokeapi.pokemon", "fields": {"name": "Samurott", "types": [11]}}, {"pk": 512, "model": "pokeapi.pokemon", "fields": {"name": "Patrat", "types": [1]}}, {"pk": 513, "model": "pokeapi.pokemon", "fields": {"name": "Stunky", "types": [4, 17]}}, {"pk": 514, "model": "pokeapi.pokemon", "fields": {"name": "Thundurus", "types": [3, 13]}}, {"pk": 515, "model": "pokeapi.pokemon", "fields": {"name": "Chespin", "types": [12]}}, {"pk": 516, "model": "pokeapi.pokemon", "fields": {"name": "Pancham", "types": [19]}}, {"pk": 517, "model": "pokeapi.pokemon", "fields": {"name": "Spritzee", "types": [18]}}, {"pk": 518, "model": "pokeapi.pokemon", "fields": {"name": "Sableye", "types": [8, 17]}}, {"pk": 519, "model": "pokeapi.pokemon", "fields": {"name": "Bronzor", "types": [9, 14]}}, {"pk": 520, "model": "pokeapi.pokemon", "fields": {"name": "Dugtrio", "types": [5]}}, {"pk": 521, "model": "pokeapi.pokemon", "fields": {"name": "Typhlosion", "types": [10]}}, {"pk": 522, "model": "pokeapi.pokemon", "fields": {"name": "Golurk", "types": [5, 8]}}, {"pk": 523, "model": "pokeapi.pokemon", "fields": {"name": "Dwebble", "types": [6, 7]}}, {"pk": 524, "model": "pokeapi.pokemon", "fields": {"name": "Scizor", "types": [7, 9]}}, {"pk": 525, "model": "pokeapi.pokemon", "fields": {"name": "Persian", "types": [1]}}, {"pk": 526, "model": "pokeapi.pokemon", "fields": {"name": "Nidoking", "types": [4, 5]}}, {"pk": 527, "model": "pokeapi.pokemon", "fields": {"name": "Zapdos", "types": [3, 13]}}, {"pk": 528, "model": "pokeapi.pokemon", "fields": {"name": "Ninjask", "types": [3, 7]}}, {"pk": 529, "model": "pokeapi.pokemon", "fields": {"name": "Grovyle", "types": [12]}}, {"pk": 530, "model": "pokeapi.pokemon", "fields": {"name": "Tyranitar", "types": [6, 17]}}, {"pk": 531, "model": "pokeapi.pokemon", "fields": {"name": "Karrablast", "types": [7]}}, {"pk": 532, "model": "pokeapi.pokemon", "fields": {"name": "Nincada", "types": [5, 7]}}, {"pk": 533, "model": "pokeapi.pokemon", "fields": {"name": "Grumpig", "types": [14]}}, {"pk": 534, "model": "pokeapi.pokemon", "fields": {"name": "Moltres", "types": [3, 10]}}, {"pk": 535, "model": "pokeapi.pokemon", "fields": {"name": "Flareon", "types": [10]}}, {"pk": 536, "model": "pokeapi.pokemon", "fields": {"name": "Kabuto", "types": [6, 11]}}, {"pk": 537, "model": "pokeapi.pokemon", "fields": {"name": "Turtwig", "types": [12]}}, {"pk": 538, "model": "pokeapi.pokemon", "fields": {"name": "Registeel", "types": [9]}}, {"pk": 539, "model": "pokeapi.pokemon", "fields": {"name": "Fraxure", "types": [16]}}, {"pk": 540, "model": "pokeapi.pokemon", "fields": {"name": "Stantler", "types": [1]}}, {"pk": 541, "model": "pokeapi.pokemon", "fields": {"name": "Shinx", "types": [13]}}, {"pk": 542, "model": "pokeapi.pokemon", "fields": {"name": "Delibird", "types": [3, 15]}}, {"pk": 543, "model": "pokeapi.pokemon", "fields": {"name": "Glameow", "types": [1]}}, {"pk": 544, "model": "pokeapi.pokemon", "fields": {"name": "Helioptile", "types": [1, 13]}}, {"pk": 545, "model": "pokeapi.pokemon", "fields": {"name": "Charizard", "types": [3, 10]}}, {"pk": 546, "model": "pokeapi.pokemon", "fields": {"name": "Minccino", "types": [1]}}, {"pk": 547, "model": "pokeapi.pokemon", "fields": {"name": "Magmortar", "types": [10]}}, {"pk": 548, "model": "pokeapi.pokemon", "fields": {"name": "Abomasnow", "types": [12, 15]}}, {"pk": 549, "model": "pokeapi.pokemon", "fields": {"name": "Petilil", "types": [12]}}, {"pk": 550, "model": "pokeapi.pokemon", "fields": {"name": "Luxray", "types": [13]}}, {"pk": 551, "model": "pokeapi.pokemon", "fields": {"name": "Jellicent", "types": [8, 11]}}, {"pk": 552, "model": "pokeapi.pokemon", "fields": {"name": "Mienshao", "types": [19]}}, {"pk": 553, "model": "pokeapi.pokemon", "fields": {"name": "Honedge", "types": [8, 9]}}, {"pk": 554, "model": "pokeapi.pokemon", "fields": {"name": "Sentret", "types": [1]}}, {"pk": 555, "model": "pokeapi.pokemon", "fields": {"name": "Snover", "types": [12, 15]}}, {"pk": 556, "model": "pokeapi.pokemon", "fields": {"name": "Gogoat", "types": [12]}}, {"pk": 557, "model": "pokeapi.pokemon", "fields": {"name": "Flygon", "types": [5, 16]}}, {"pk": 558, "model": "pokeapi.pokemon", "fields": {"name": "Skorupi", "types": [4, 7]}}, {"pk": 559, "model": "pokeapi.pokemon", "fields": {"name": "Escavalier", "types": [7, 9]}}, {"pk": 560, "model": "pokeapi.pokemon", "fields": {"name": "Sliggoo", "types": [16]}}, {"pk": 561, "model": "pokeapi.pokemon", "fields": {"name": "Latias", "types": [14, 16]}}, {"pk": 562, "model": "pokeapi.pokemon", "fields": {"name": "Landorus", "types": [3, 5]}}, {"pk": 563, "model": "pokeapi.pokemon", "fields": {"name": "Zigzagoon", "types": [1]}}, {"pk": 564, "model": "pokeapi.pokemon", "fields": {"name": "Lugia", "types": [3, 14]}}, {"pk": 565, "model": "pokeapi.pokemon", "fields": {"name": "Onix", "types": [5, 6]}}, {"pk": 566, "model": "pokeapi.pokemon", "fields": {"name": "Clefairy", "types": [18]}}, {"pk": 567, "model": "pokeapi.pokemon", "fields": {"name": "Grimer", "types": [4]}}, {"pk": 568, "model": "pokeapi.pokemon", "fields": {"name": "Bagon", "types": [16]}}, {"pk": 569, "model": "pokeapi.pokemon", "fields": {"name": "Magneton", "types": [9, 13]}}, {"pk": 570, "model": "pokeapi.pokemon", "fields": {"name": "Forretress", "types": [7, 9]}}, {"pk": 571, "model": "pokeapi.pokemon", "fields": {"name": "Skarmory", "types": [3, 9]}}, {"pk": 572, "model": "pokeapi.pokemon", "fields": {"name": "Goomy", "types": [16]}}, {"pk": 573, "model": "pokeapi.pokemon", "fields": {"name": "Mime Jr", "types": [14]}}, {"pk": 574, "model": "pokeapi.pokemon", "fields": {"name": "Volbeat", "types": [7]}}, {"pk": 575, "model": "pokeapi.pokemon", "fields": {"name": "Loudred", "types": [1]}}, {"pk": 576, "model": "pokeapi.pokemon", "fields": {"name": "Archeops", "types": [3, 6]}}, {"pk": 577, "model": "pokeapi.pokemon", "fields": {"name": "Bronzong", "types": [9, 14]}}, {"pk": 578, "model": "pokeapi.pokemon", "fields": {"name": "Delcatty", "types": [1]}}, {"pk": 579, "model": "pokeapi.pokemon", "fields": {"name": "Machop", "types": [19]}}, {"pk": 580, "model": "pokeapi.pokemon", "fields": {"name": "Mightyena", "types": [17]}}, {"pk": 581, "model": "pokeapi.pokemon", "fields": {"name": "Spinarak", "types": [4, 7]}}, {"pk": 582, "model": "pokeapi.pokemon", "fields": {"name": "Growlithe", "types": [10]}}, {"pk": 583, "model": "pokeapi.pokemon", "fields": {"name": "Munna", "types": [14]}}, {"pk": 584, "model": "pokeapi.pokemon", "fields": {"name": "Wynaut", "types": [14]}}, {"pk": 585, "model": "pokeapi.pokemon", "fields": {"name": "Cacnea", "types": [12]}}, {"pk": 586, "model": "pokeapi.pokemon", "fields": {"name": "Purrloin", "types": [17]}}, {"pk": 587, "model": "pokeapi.pokemon", "fields": {"name": "Rayquaza", "types": [3, 16]}}, {"pk": 588, "model": "pokeapi.pokemon", "fields": {"name": "Dragonair", "types": [16]}}, {"pk": 589, "model": "pokeapi.pokemon", "fields": {"name": "Diggersby", "types": [1, 5]}}, {"pk": 590, "model": "pokeapi.pokemon", "fields": {"name": "Garchomp", "types": [5, 16]}}, {"pk": 591, "model": "pokeapi.pokemon", "fields": {"name": "Zekrom", "types": [13, 16]}}, {"pk": 592, "model": "pokeapi.pokemon", "fields": {"name": "Wurmple", "types": [7]}}, {"pk": 593, "model": "pokeapi.pokemon", "fields": {"name": "Cinccino", "types": [1]}}, {"pk": 594, "model": "pokeapi.pokemon", "fields": {"name": "Tentacool", "types": [4, 11]}}, {"pk": 595, "model": "pokeapi.pokemon", "fields": {"name": "Scrafty", "types": [17, 19]}}, {"pk": 596, "model": "pokeapi.pokemon", "fields": {"name": "Lilligant", "types": [12]}}, {"pk": 597, "model": "pokeapi.pokemon", "fields": {"name": "Bouffalant", "types": [1]}}, {"pk": 598, "model": "pokeapi.pokemon", "fields": {"name": "Lileep", "types": [6, 12]}}, {"pk": 599, "model": "pokeapi.pokemon", "fields": {"name": "Magmar", "types": [10]}}, {"pk": 600, "model": "pokeapi.pokemon", "fields": {"name": "Lucario", "types": [9, 19]}}, {"pk": 601, "model": "pokeapi.pokemon", "fields": {"name": "Rampardos", "types": [6]}}, {"pk": 602, "model": "pokeapi.pokemon", "fields": {"name": "Feebas", "types": [11]}}, {"pk": 603, "model": "pokeapi.pokemon", "fields": {"name": "Charmeleon", "types": [10]}}, {"pk": 604, "model": "pokeapi.pokemon", "fields": {"name": "Torterra", "types": [5, 12]}}, {"pk": 605, "model": "pokeapi.pokemon", "fields": {"name": "Scolipede", "types": [4, 7]}}, {"pk": 606, "model": "pokeapi.pokemon", "fields": {"name": "Serperior", "types": [12]}}, {"pk": 607, "model": "pokeapi.pokemon", "fields": {"name": "Shieldon", "types": [6, 9]}}, {"pk": 608, "model": "pokeapi.pokemon", "fields": {"name": "Palpitoad", "types": [5, 11]}}, {"pk": 609, "model": "pokeapi.pokemon", "fields": {"name": "Phione", "types": [11]}}, {"pk": 610, "model": "pokeapi.pokemon", "fields": {"name": "Froslass", "types": [8, 15]}}, {"pk": 611, "model": "pokeapi.pokemon", "fields": {"name": "Oshawott", "types": [11]}}, {"pk": 612, "model": "pokeapi.pokemon", "fields": {"name": "Shelmet", "types": [7]}}, {"pk": 613, "model": "pokeapi.pokemon", "fields": {"name": "Giratina", "types": [8, 16]}}, {"pk": 614, "model": "pokeapi.pokemon", "fields": {"name": "Ludicolo", "types": [11, 12]}}, {"pk": 615, "model": "pokeapi.pokemon", "fields": {"name": "Cloyster", "types": [11, 15]}}, {"pk": 616, "model": "pokeapi.pokemon", "fields": {"name": "Vibrava", "types": [5, 16]}}, {"pk": 617, "model": "pokeapi.pokemon", "fields": {"name": "Salamence", "types": [3, 16]}}, {"pk": 618, "model": "pokeapi.pokemon", "fields": {"name": "Haxorus", "types": [16]}}, {"pk": 619, "model": "pokeapi.pokemon", "fields": {"name": "Yamask", "types": [8]}}, {"pk": 620, "model": "pokeapi.pokemon", "fields": {"name": "Garbodor", "types": [4]}}, {"pk": 621, "model": "pokeapi.pokemon", "fields": {"name": "Marowak", "types": [5]}}, {"pk": 622, "model": "pokeapi.pokemon", "fields": {"name": "Glaceon", "types": [15]}}, {"pk": 623, "model": "pokeapi.pokemon", "fields": {"name": "Litleo", "types": [1, 10]}}, {"pk": 624, "model": "pokeapi.pokemon", "fields": {"name": "Surskit", "types": [7, 11]}}, {"pk": 625, "model": "pokeapi.pokemon", "fields": {"name": "Croconaw", "types": [11]}}, {"pk": 626, "model": "pokeapi.pokemon", "fields": {"name": "Graveler", "types": [5, 6]}}, {"pk": 627, "model": "pokeapi.pokemon", "fields": {"name": "Happiny", "types": [1]}}, {"pk": 628, "model": "pokeapi.pokemon", "fields": {"name": "Darkrai", "types": [17]}}, {"pk": 629, "model": "pokeapi.pokemon", "fields": {"name": "Mew", "types": [14]}}, {"pk": 630, "model": "pokeapi.pokemon", "fields": {"name": "Pidgey", "types": [1, 3]}}, {"pk": 631, "model": "pokeapi.pokemon", "fields": {"name": "Hippowdon", "types": [5]}}, {"pk": 632, "model": "pokeapi.pokemon", "fields": {"name": "Bellossom", "types": [12]}}, {"pk": 633, "model": "pokeapi.pokemon", "fields": {"name": "Blissey", "types": [1]}}, {"pk": 634, "model": "pokeapi.pokemon", "fields": {"name": "Xerneas", "types": [18]}}, {"pk": 635, "model": "pokeapi.pokemon", "fields": {"name": "Darumaka", "types": [10]}}, {"pk": 636, "model": "pokeapi.pokemon", "fields": {"name": "Gabite", "types": [5, 16]}}, {"pk": 637, "model": "pokeapi.pokemon", "fields": {"name": "Tyrunt", "types": [6, 16]}}, {"pk": 638, "model": "pokeapi.pokemon", "fields": {"name": "Victini", "types": [10, 14]}}, {"pk": 639, "model": "pokeapi.pokemon", "fields": {"name": "Lanturn", "types": [11, 13]}}, {"pk": 640, "model": "pokeapi.pokemon", "fields": {"name": "Litwick", "types": [8, 10]}}, {"pk": 641, "model": "pokeapi.pokemon", "fields": {"name": "Quilladin", "types": [12]}}, {"pk": 642, "model": "pokeapi.pokemon", "fields": {"name": "Zweilous", "types": [16, 17]}}, {"pk": 643, "model": "pokeapi.pokemon", "fields": {"name": "Beautifly", "types": [3, 7]}}, {"pk": 644, "model": "pokeapi.pokemon", "fields": {"name": "Meowth", "types": [1]}}, {"pk": 645, "model": "pokeapi.pokemon", "fields": {"name": "Delphox", "types": [10, 14]}}, {"pk": 646, "model": "pokeapi.pokemon", "fields": {"name": "Herdier", "types": [1]}}, {"pk": 647, "model": "pokeapi.pokemon", "fields": {"name": "Pelipper", "types": [3, 11]}}, {"pk": 648, "model": "pokeapi.pokemon", "fields": {"name": "Avalugg", "types": [15]}}, {"pk": 649, "model": "pokeapi.pokemon", "fields": {"name": "Nolvern", "types": [3, 16]}}, {"pk": 650, "model": "pokeapi.pokemon", "fields": {"name": "Swalot", "types": [4]}}, {"pk": 651, "model": "pokeapi.pokemon", "fields": {"name": "Zygarde", "types": [5, 16]}}, {"pk": 652, "model": "pokeapi.pokemon", "fields": {"name": "Meganium", "types": [12]}}, {"pk": 653, "model": "pokeapi.pokemon", "fields": {"name": "Monferno", "types": [10, 19]}}, {"pk": 654, "model": "pokeapi.pokemon", "fields": {"name": "Joltik", "types": [7, 13]}}, {"pk": 655, "model": "pokeapi.pokemon", "fields": {"name": "Barbaracle", "types": [6, 11]}}, {"pk": 656, "model": "pokeapi.pokemon", "fields": {"name": "Drowzee", "types": [14]}}, {"pk": 657, "model": "pokeapi.pokemon", "fields": {"name": "Yveltal", "types": [3, 17]}}, {"pk": 658, "model": "pokeapi.pokemon", "fields": {"name": "Ho-oh", "types": [3, 10]}}, {"pk": 659, "model": "pokeapi.pokemon", "fields": {"name": "Simisear", "types": [10]}}, {"pk": 660, "model": "pokeapi.pokemon", "fields": {"name": "Mienfoo", "types": [19]}}, {"pk": 661, "model": "pokeapi.pokemon", "fields": {"name": "Chandelure", "types": [8, 10]}}, {"pk": 662, "model": "pokeapi.pokemon", "fields": {"name": "Staraptor", "types": [1, 3]}}, {"pk": 663, "model": "pokeapi.pokemon", "fields": {"name": "Elekid", "types": [13]}}, {"pk": 664, "model": "pokeapi.pokemon", "fields": {"name": "Ursaring", "types": [1]}}, {"pk": 665, "model": "pokeapi.pokemon", "fields": {"name": "Anorith", "types": [6, 7]}}, {"pk": 666, "model": "pokeapi.pokemon", "fields": {"name": "Tyrantrum", "types": [6, 16]}}, {"pk": 667, "model": "pokeapi.pokemon", "fields": {"name": "Haunter", "types": [4, 8]}}, {"pk": 668, "model": "pokeapi.pokemon", "fields": {"name": "Tynamo", "types": [13]}}, {"pk": 669, "model": "pokeapi.pokemon", "fields": {"name": "Combee", "types": [3, 7]}}, {"pk": 670, "model": "pokeapi.pokemon", "fields": {"name": "Krokorok", "types": [5, 17]}}, {"pk": 671, "model": "pokeapi.pokemon", "fields": {"name": "Amaura", "types": [6, 15]}}, {"pk": 672, "model": "pokeapi.pokemon", "fields": {"name": "Mewtwo", "types": [14]}}, {"pk": 673, "model": "pokeapi.pokemon", "fields": {"name": "Tranquill", "types": [1, 3]}}, {"pk": 674, "model": "pokeapi.pokemon", "fields": {"name": "Riolu", "types": [19]}}, {"pk": 675, "model": "pokeapi.pokemon", "fields": {"name": "Combusken", "types": [10, 19]}}, {"pk": 676, "model": "pokeapi.pokemon", "fields": {"name": "Aromatisse", "types": [18]}}, {"pk": 677, "model": "pokeapi.pokemon", "fields": {"name": "Scatterbug", "types": [7]}}, {"pk": 678, "model": "pokeapi.pokemon", "fields": {"name": "Castform", "types": [1]}}, {"pk": 679, "model": "pokeapi.pokemon", "fields": {"name": "Numel", "types": [5, 10]}}, {"pk": 680, "model": "pokeapi.pokemon", "fields": {"name": "Spinda", "types": [1]}}, {"pk": 681, "model": "pokeapi.pokemon", "fields": {"name": "Sharpedo", "types": [11, 17]}}, {"pk": 682, "model": "pokeapi.pokemon", "fields": {"name": "Cradily", "types": [6, 12]}}, {"pk": 683, "model": "pokeapi.pokemon", "fields": {"name": "Pidgeot", "types": [1, 3]}}, {"pk": 684, "model": "pokeapi.pokemon", "fields": {"name": "Kingler", "types": [11]}}, {"pk": 685, "model": "pokeapi.pokemon", "fields": {"name": "Exeggcute", "types": [12, 14]}}, {"pk": 686, "model": "pokeapi.pokemon", "fields": {"name": "Fearow", "types": [1, 3]}}, {"pk": 687, "model": "pokeapi.pokemon", "fields": {"name": "Lunatone", "types": [6, 14]}}, {"pk": 688, "model": "pokeapi.pokemon", "fields": {"name": "Roserade", "types": [4, 12]}}, {"pk": 689, "model": "pokeapi.pokemon", "fields": {"name": "Vanillite", "types": [15]}}, {"pk": 690, "model": "pokeapi.pokemon", "fields": {"name": "Rapidash", "types": [10]}}, {"pk": 691, "model": "pokeapi.pokemon", "fields": {"name": "Golett", "types": [5, 8]}}, {"pk": 692, "model": "pokeapi.pokemon", "fields": {"name": "Krabby", "types": [11]}}, {"pk": 693, "model": "pokeapi.pokemon", "fields": {"name": "Electivire", "types": [13]}}, {"pk": 694, "model": "pokeapi.pokemon", "fields": {"name": "Skitty", "types": [1]}}, {"pk": 695, "model": "pokeapi.pokemon", "fields": {"name": "Seadra", "types": [11]}}, {"pk": 696, "model": "pokeapi.pokemon", "fields": {"name": "Tirtouga", "types": [6, 11]}}, {"pk": 697, "model": "pokeapi.pokemon", "fields": {"name": "Donphan", "types": [5]}}, {"pk": 698, "model": "pokeapi.pokemon", "fields": {"name": "Hoppip", "types": [3, 12]}}, {"pk": 699, "model": "pokeapi.pokemon", "fields": {"name": "Tornadus", "types": [3]}}, {"pk": 700, "model": "pokeapi.pokemon", "fields": {"name": "Whismur", "types": [1]}}, {"pk": 701, "model": "pokeapi.pokemon", "fields": {"name": "Gastrodon", "types": [5, 11]}}, {"pk": 702, "model": "pokeapi.pokemon", "fields": {"name": "Victreebel", "types": [4, 12]}}, {"pk": 703, "model": "pokeapi.pokemon", "fields": {"name": "Natu", "types": [3, 14]}}, {"pk": 704, "model": "pokeapi.pokemon", "fields": {"name": "Carnivine", "types": [12]}}, {"pk": 705, "model": "pokeapi.pokemon", "fields": {"name": "Shaymin", "types": [12]}}, {"pk": 706, "model": "pokeapi.pokemon", "fields": {"name": "Drilbur", "types": [5]}}, {"pk": 707, "model": "pokeapi.pokemon", "fields": {"name": "Bidoof", "types": [1]}}, {"pk": 708, "model": "pokeapi.pokemon", "fields": {"name": "Munchlax", "types": [1]}}, {"pk": 709, "model": "pokeapi.pokemon", "fields": {"name": "Pupitar", "types": [5, 6]}}, {"pk": 710, "model": "pokeapi.pokemon", "fields": {"name": "Nuzleaf", "types": [12, 17]}}, {"pk": 711, "model": "pokeapi.pokemon", "fields": {"name": "Meditite", "types": [14, 19]}}, {"pk": 712, "model": "pokeapi.pokemon", "fields": {"name": "Weedle", "types": [4, 7]}}, {"pk": 713, "model": "pokeapi.pokemon", "fields": {"name": "Shuppet", "types": [8]}}, {"pk": 714, "model": "pokeapi.pokemon", "fields": {"name": "Kricketune", "types": [7]}}, {"pk": 715, "model": "pokeapi.pokemon", "fields": {"name": "Miltank", "types": [1]}}, {"pk": 716, "model": "pokeapi.pokemon", "fields": {"name": "Snivy", "types": [12]}}, {"pk": 717, "model": "pokeapi.pokemon", "fields": {"name": "Accelgor", "types": [7]}}, {"pk": 718, "model": "pokeapi.pokemon", "fields": {"name": "Caterpie", "types": [7]}}, {"pk": 719, "model": "pokeapi.pokemon", "fields": {"name": "Froakie", "types": [11]}}, {"pk": 720, "model": "pokeapi.pokemon", "fields": {"name": "Kyogre", "types": [11]}}, {"pk": 721, "model": "pokeapi.pokemon", "fields": {"name": "Simipour", "types": [11]}}, {"pk": 722, "model": "pokeapi.pokemon", "fields": {"name": "Cranidos", "types": [6]}}, {"pk": 723, "model": "pokeapi.pokemon", "fields": {"name": "Dewgong", "types": [11, 15]}}, {"pk": 724, "model": "pokeapi.pokemon", "fields": {"name": "Muk", "types": [4]}}, {"pk": 725, "model": "pokeapi.pokemon", "fields": {"name": "Shiftry", "types": [12, 17]}}, {"pk": 726, "model": "pokeapi.pokemon", "fields": {"name": "Cryogonal", "types": [15]}}, {"pk": 727, "model": "pokeapi.pokemon", "fields": {"name": "Beartic", "types": [15]}}, {"pk": 728, "model": "pokeapi.pokemon", "fields": {"name": "Rhyhorn", "types": [5, 6]}}, {"pk": 729, "model": "pokeapi.pokemon", "fields": {"name": "Torchic", "types": [10]}}, {"pk": 730, "model": "pokeapi.pokemon", "fields": {"name": "Tentacruel", "types": [4, 11]}}, {"pk": 731, "model": "pokeapi.pokemon", "fields": {"name": "Armaldo", "types": [6, 7]}}, {"pk": 732, "model": "pokeapi.pokemon", "fields": {"name": "Espeon", "types": [14]}}, {"pk": 733, "model": "pokeapi.pokemon", "fields": {"name": "Cubone", "types": [5]}}, {"pk": 734, "model": "pokeapi.pokemon", "fields": {"name": "Wigglytuff", "types": [1]}}, {"pk": 735, "model": "pokeapi.pokemon", "fields": {"name": "Flabebe", "types": [18]}}, {"pk": 736, "model": "pokeapi.pokemon", "fields": {"name": "Watchog", "types": [1]}}, {"pk": 737, "model": "pokeapi.pokemon", "fields": {"name": "Shedinja", "types": [7, 8]}}, {"pk": 738, "model": "pokeapi.pokemon", "fields": {"name": "Swampert", "types": [5, 11]}}, {"pk": 739, "model": "pokeapi.pokemon", "fields": {"name": "Sneasel", "types": [15, 17]}}, {"pk": 740, "model": "pokeapi.pokemon", "fields": {"name": "Ledyba", "types": [3, 7]}}, {"pk": 741, "model": "pokeapi.pokemon", "fields": {"name": "Hitmontop", "types": [19]}}, {"pk": 742, "model": "pokeapi.pokemon", "fields": {"name": "Kingdra", "types": [11, 16]}}]